[
  {
    "id": "6",
    "title": "Metis Hyperion: HyperHack",
    "description": "A three-month hackathon for building AI-native and high-performance dApps on the Hyperion blockchain.",
    "startDate": "2025-05-15T00:00:00Z",
    "endDate": "2025-08-07T23:59:00Z",
    "registrationEndDate": "2025-06-15T23:59:00Z",
    "platform": "devfolio",
    "url": "https://metis-hyperhack.devfolio.co/",
    "location": "Online",
    "teamSize": "1-4 members",
    "prizePool": "$200,000",
    "status": "registration_open"
  },
  {
    "id": "10",
    "title": "Lisk Builders Challenge: Round Two",
    "description": "A 3-month blockchain hackathon for Southeast Asia, empowering devs to build Web3 consumer apps and localized DeFi solutions.",
    "startDate": "2025-06-10T00:00:00Z",
    "endDate": "2025-08-03T23:59:00Z",
    "registrationEndDate": "2025-08-03T23:59:00Z",
    "platform": "devfolio",
    "url": "https://lisk-builders-challenge-2.devfolio.co/",
    "location": "Online",
    "teamSize": "1-5 members",
    "prizePool": "$6,800",
    "status": "registration_open"
  },
  {
    "id": "34",
    "title": "ComSoc HackX 2025",
    "description": "A national 36-hour hackathon by IEEE ComSoc Chandigarh University. Compete across AI, Blockchain, IoT, and more to win prizes and internship offers.",
    "startDate": "2025-06-15T00:00:00+05:30",
    "endDate": "2025-08-03T16:30:00+05:30",
    "registrationEndDate": "2025-06-30T23:55:00+05:30",
    "platform": "unstop",
    "url": "https://unstop.com/hackathons/comsoc-hackx-2025-chandigarh-university-cu-ajitgarh-punjab-1412240",
    "location": "Online + Offline (Chandigarh University)",
    "teamSize": "3-5 members",
    "prizePool": "\u20b960,000 + internships + free premium courses + goodies",
    "status": "registration_open"
  },
  {
    "id": "27",
    "title": "Incubate 2025",
    "description": "IIT Bombay's MedTech Hackathon with JIPMER empowers mixed medical-engineering teams to innovate health-tech solutions with mentorship and funding.",
    "startDate": "2025-06-20T00:00:00+05:30",
    "endDate": "2025-10-15T00:00:00+05:30",
    "registrationEndDate": "2025-07-04T00:00:00+05:30",
    "platform": "unstop",
    "url": "https://unstop.com/hackathons/incubate-2025-iit-bombay-1505912",
    "location": "Online + Onsite (JIPMER)",
    "teamSize": "2-4 members (min 1 medical + 1 engineering student)",
    "prizePool": "Prototype funding + travel + certificates",
    "status": "registration_open"
  },
  {
    "id": "18",
    "title": "Ozibook Hiring Challenge June 2025",
    "description": "A hiring hackathon offering real-world problem solving, with a chance to win a PPO at Ozibook Tech Solutions and its partner companies.",
    "startDate": "2025-06-22T20:00:00+05:30",
    "endDate": "2025-07-07T20:00:00+05:30",
    "registrationEndDate": "2025-06-26T15:00:00+05:30",
    "platform": "unstop",
    "url": "https://unstop.com/hackathons/ozibook-hiring-challenge-june-2025-ozibook-tech-solutions-private-limited-1502786",
    "location": "Online",
    "teamSize": "1-4 members",
    "prizePool": "Pre-Placement Offers + Certificates",
    "status": "registration_open"
  },
  {
    "id": "21",
    "title": "Code & Conquer: 24-Hour Hackathon",
    "description": "A high-stakes hackathon by FairSeat focused on Web3, AI for Social Good, Smart Ticketing, and Climate Tech, with live demo day at IIT Delhi.",
    "startDate": "2025-06-23T00:30:00+05:30",
    "endDate": "2025-08-17T00:00:00+05:30",
    "registrationEndDate": "2025-06-25T15:00:00+05:30",
    "platform": "unstop",
    "url": "https://unstop.com/hackathons/code-conquer-24-hour-hackathon-fairseat-1505405",
    "location": "Hybrid (Online + Offline at IIT Delhi)",
    "teamSize": "1-4 members",
    "prizePool": "\u20b93,00,000 + Internships + Swags",
    "status": "registration_open"
  },
  {
    "id": "19",
    "title": "Atria's Innovathon",
    "description": "A two-phase innovation challenge by Atria University where students solve real-world issues for scholarships and global university networking.",
    "startDate": "2025-06-23T11:23:00+05:30",
    "endDate": "2025-07-12T17:00:00+05:30",
    "registrationEndDate": "2025-07-06T00:00:00+05:30",
    "platform": "unstop",
    "url": "https://unstop.com/hackathons/atrias-innovathon-atria-future-fest-atria-university-1506912",
    "location": "Bangalore, India",
    "teamSize": "4-5 members",
    "prizePool": "Scholarships + cash + networking",
    "status": "registration_open"
  },
  {
    "id": "16",
    "title": "RailHack 2025",
    "description": "RailHack 2025 is a 24-hour innovation challenge focused on reimagining Indian Railways through smart, sustainable, and secure solutions.",
    "startDate": "2025-06-25T15:00:00+05:30",
    "endDate": "2025-06-25T17:00:00+05:30",
    "registrationEndDate": "2025-06-25T13:00:00+05:30",
    "platform": "unstop",
    "url": "https://unstop.com/hackathons/railhack-2025-gla-university-glau-uttar-pradesh-1507238",
    "location": "Online",
    "teamSize": "1-4 members",
    "prizePool": "\u20b93,000 + trophies + certificates",
    "status": "registration_open"
  },
  {
    "id": "23",
    "title": "Open Source Hackathon",
    "description": "CertifyO's open hackathon welcomes solo and team participation to build or contribute to open source projects using any stack.",
    "startDate": "2025-06-29T10:30:00+05:30",
    "endDate": "2025-06-29T23:59:00+05:30",
    "registrationEndDate": "2025-06-28T23:59:00+05:30",
    "platform": "unstop",
    "url": "https://unstop.com/hackathons/open-source-hackathon-certifyo-1506468",
    "location": "Online",
    "teamSize": "1-4 members",
    "prizePool": "\u20b915,000 worth of tools & subscriptions",
    "status": "registration_open"
  },
  {
    "id": "20",
    "title": "InsureBot Quest 2025 - Hackathon | Conversational Bot",
    "description": "ValuEnable invites AI enthusiasts to build a conversational voice AI bot for the insurance sector using real-life recordings and knowledge bases.",
    "startDate": "2025-07-05T00:00:00+05:30",
    "endDate": "2025-08-12T00:00:00+05:30",
    "registrationEndDate": "2025-07-04T00:00:00+05:30",
    "platform": "unstop",
    "url": "https://unstop.com/hackathons/insurebot-quest-2025-hackathon-conversational-bot-valuenable-pvt-ltd-1505397",
    "location": "Online",
    "teamSize": "1-3 members",
    "prizePool": "\u20b950,000 + Certificate + Website Recognition",
    "status": "registration_open"
  },
  {
    "id": "29",
    "title": "'AI for Quality' Hackathon",
    "description": "A multi-stage challenge to build an AI-powered assistant focused on quality learning, diagnosis, and improvement. Finalists will pitch live at BMU, Gurgaon.",
    "startDate": "2025-07-05T18:00:00+05:30",
    "endDate": "2025-09-17T18:00:00+05:30",
    "registrationEndDate": "2025-07-05T16:00:00+05:30",
    "platform": "unstop",
    "url": "https://unstop.com/hackathons/ai-for-quality-hackathon-ifqm-conclave-for-academia-2025-in-collaboration-with-bmu-ifqm-1503880",
    "location": "Online + Onsite (BMU Gurgaon)",
    "teamSize": "2-3 members (same institution)",
    "prizePool": "\u20b925,000 in gift vouchers + IFQM Symposium invites",
    "status": "registration_open"
  },
  {
    "id": "17",
    "title": "HackOrbit 2025 \u2013 National Hackathon",
    "description": "A national-level hackathon hosted by MITS Gwalior focused on AI, Blockchain, Fintech, and Sustainability, offering \u20b925,000 in prizes and goodies.",
    "startDate": "2025-07-06T07:06:00+05:30",
    "endDate": "2025-07-08T07:06:00+05:30",
    "registrationEndDate": "2025-07-04T00:21:00+05:30",
    "platform": "unstop",
    "url": "https://unstop.com/hackathons/hackorbit-2025-national-hackathon-transform-code-into-change-madhav-institute-of-technology-and-science-mits--1504440",
    "location": "Online",
    "teamSize": "1-4 members",
    "prizePool": "\u20b925,000 + goodies + digital perks",
    "status": "registration_open"
  },
  {
    "id": "28",
    "title": "Anurag University National Student Forum - AUNSF 3.0",
    "description": "A national student forum for undergrads to ideate and present sustainability-focused models with mentorship and awards across multiple domains.",
    "startDate": "2025-07-11T00:00:00+05:30",
    "endDate": "2025-07-13T23:59:00+05:30",
    "registrationEndDate": "2025-07-06T00:00:00+05:30",
    "platform": "unstop",
    "url": "https://unstop.com/hackathons/anurag-university-national-student-forum-aunsf-30-anurag-university-1505045",
    "location": "Anurag University, Hyderabad, India",
    "teamSize": "Individual Participation",
    "prizePool": "\u20b925,000 + prizes in kind",
    "status": "registration_open"
  },
  {
    "id": "26",
    "title": "Adobe India Hackathon",
    "description": "Adobe's national hackathon challenges students to build intelligent document systems with a shot at PPIs, internships, and premium prizes.",
    "startDate": "2025-07-11T12:00:00+05:30",
    "endDate": "2025-09-05T14:00:00+05:30",
    "registrationEndDate": "2025-07-10T23:59:00+05:30",
    "platform": "unstop",
    "url": "https://unstop.com/hackathons/adobe-india-hackathon-adobe-1483364",
    "location": "Online + Onsite (Noida for Finale)",
    "teamSize": "2-3 members (same college only)",
    "prizePool": "MacBooks, iPads, PPIs, \u20b91L/month internships",
    "status": "registration_open"
  },
  {
    "id": "5",
    "title": "The IndeHub Hackathon | Build With WWDC25",
    "description": "Build apps for Apple platforms using WWDC25 features in collaboration with Swift communities across India.",
    "startDate": "2025-07-12T00:00:00Z",
    "endDate": "2025-07-17T23:59:00Z",
    "registrationEndDate": "2025-07-11T23:59:00Z",
    "platform": "devfolio",
    "url": "https://wwdc25.devfolio.co/",
    "location": "Online",
    "teamSize": "1-3 members",
    "prizePool": "\u20b91,00,000",
    "status": "registration_open"
  },
  {
    "id": "33",
    "title": "Odoo Hackathon 2025",
    "description": "Odoo\u2019s national-level coding challenge with a virtual round and offline finals in Gandhinagar. Win up to \u20b93,00,000 and get internship opportunities.",
    "startDate": "2025-07-12T09:00:00+05:30",
    "endDate": "2025-08-12T17:00:00+05:30",
    "registrationEndDate": "2025-07-01T01:00:00+05:30",
    "platform": "unstop",
    "url": "https://unstop.com/hackathons/odoo-hackathon-odoo-1464473",
    "location": "Online + Offline (Gandhinagar, Gujarat)",
    "teamSize": "1-4 members",
    "prizePool": "\u20b93,00,000 + Odoo goodies + internship opportunities",
    "status": "registration_open"
  },
  {
    "id": "25",
    "title": "AMD AI Sprint - Hackathon",
    "description": "Hosted at IIT Bombay, this 2-day offline AI hackathon invites students and professionals to build agentic AI tools and compete for \u20b96 lakh.",
    "startDate": "2025-07-12T09:30:00+05:30",
    "endDate": "2025-07-13T18:00:00+05:30",
    "registrationEndDate": "2025-07-02T23:59:00+05:30",
    "platform": "unstop",
    "url": "https://unstop.com/hackathons/amd-ai-sprint-hackathon-iit-bombay-1506226",
    "location": "IIT Bombay, Mumbai, India",
    "teamSize": "2-4 members",
    "prizePool": "\u20b96,00,000",
    "status": "registration_open"
  },
  {
    "id": "30",
    "title": "Juspay Hiring Challenge 2025",
    "description": "An exclusive hiring challenge for 2026 batch students, offering high-paying internships and PPOs up to \u20b927 LPA through coding and MCQ rounds.",
    "startDate": "2025-07-13T00:00:00+05:30",
    "endDate": "2025-09-30T00:00:00+05:30",
    "registrationEndDate": "2025-07-13T23:59:00+05:30",
    "platform": "unstop",
    "url": "https://unstop.com/competitions/juspay-hiring-challenge-2025-juspay-1466934",
    "location": "Online",
    "teamSize": "Individual Participation",
    "prizePool": "PPOs worth \u20b921\u201327 LPA + \u20b940k/month internship",
    "status": "registration_open"
  },
  {
    "id": "22",
    "title": "CustomerConnect: The AI Agents Revolution in Support",
    "description": "Build functional AI agents for customer support during a 12-hour hackathon in Bengaluru. Includes tracks like smart FAQ, sentiment analysis, order tracking, and complaint categorization.",
    "startDate": "2025-07-15T09:00:00+05:30",
    "endDate": "2025-07-15T21:00:00+05:30",
    "registrationEndDate": "2025-07-13T23:59:00+05:30",
    "platform": "unstop",
    "url": "https://unstop.com/hackathons/customerconnect-the-ai-agents-revolution-in-support-proptelligence-technologies-1506476",
    "location": "Bengaluru, India",
    "teamSize": "1-2 members",
    "prizePool": "\u20b917,500 + Certificates + Swags",
    "status": "registration_open"
  },
  {
    "id": "8",
    "title": "DEVMatch Hackathon 2025",
    "description": "Malaysia\u2019s largest student blockchain hackathon with 168 hours of innovation, workshops, and real-world challenge solving.",
    "startDate": "2025-08-02T00:00:00Z",
    "endDate": "2025-08-10T23:59:00Z",
    "registrationEndDate": "2025-08-01T23:59:00Z",
    "platform": "devfolio",
    "url": "https://devmatch-hackathon.devfolio.co/",
    "location": "Online",
    "teamSize": "2-5 members",
    "prizePool": "$8,100",
    "status": "registration_open"
  },
  {
    "id": "24",
    "title": "Design Hackathon 2025",
    "description": "DQ Labs\u2019 DH25 promotes design thinking through guided problem-solving across multiple participant categories with mentorship and rewards.",
    "startDate": "2025-08-02T10:00:00+05:30",
    "endDate": "2025-08-03T18:00:00+05:30",
    "registrationEndDate": "2025-07-21T00:00:00+05:30",
    "platform": "unstop",
    "url": "https://unstop.com/hackathons/design-hackathon-2025-dq-labs-private-limited-1503763",
    "location": "Online",
    "teamSize": "1-5 members (same category)",
    "prizePool": "\u20b93,64,000 across 6 categories + trophies",
    "status": "registration_open"
  },
  {
    "id": "11",
    "title": "Hack The Horizon 2.0 (VIT-Chennai)",
    "description": "A 24-hour hackathon by the AI Club of VIT Chennai for developers passionate about AI, software, and sustainable tech.",
    "startDate": "2025-08-13T00:00:00Z",
    "endDate": "2025-08-14T23:59:00Z",
    "registrationEndDate": "2025-08-12T23:59:00Z",
    "platform": "devfolio",
    "url": "https://hack-the-horizon-2.devfolio.co/",
    "location": "Chennai, India",
    "teamSize": "2-4 members",
    "prizePool": "$100",
    "status": "registration_open"
  },
  {
    "id": "7",
    "title": ".hack(); 25",
    "description": "The 6th edition of IEEE MACE SB\u2019s hackathon focused on innovative tech solutions to social challenges, blending learning, networking, and impact.",
    "startDate": "2025-08-22T00:00:00Z",
    "endDate": "2025-08-24T23:59:00Z",
    "registrationEndDate": "2025-08-21T23:59:00Z",
    "platform": "devfolio",
    "url": "https://hack25.devfolio.co/",
    "location": "Kothamangalam, India",
    "teamSize": "1-4 members",
    "prizePool": "$1,266",
    "status": "registration_open"
  },
  {
    "id": "12",
    "title": "StatusCode 2",
    "description": "A 36-hour hackathon by IIIT Kalyani where developers compete and collaborate to build industry-relevant solutions.",
    "startDate": "2025-08-23T00:00:00Z",
    "endDate": "2025-08-24T23:59:00Z",
    "registrationEndDate": "2025-08-22T23:59:00Z",
    "platform": "devfolio",
    "url": "https://statuscode-2.devfolio.co/",
    "location": "Mohanpur, India",
    "teamSize": "2-5 members",
    "prizePool": "$100",
    "status": "registration_open"
  },
  {
    "id": "9",
    "title": "Hack4Maharashtra",
    "description": "Maharashtra\u2019s 24-hour hackathon celebrating innovation through local culture, identity, and game-inspired tech solutions.",
    "startDate": "2025-08-25T00:00:00Z",
    "endDate": "2025-08-26T23:59:00Z",
    "registrationEndDate": "2025-08-24T23:59:00Z",
    "platform": "devfolio",
    "url": "https://hack4maharashtra.devfolio.co/",
    "location": "Nagpur, India",
    "teamSize": "3-4 members",
    "prizePool": "$100",
    "status": "registration_open"
  },
  {
    "id": "31",
    "title": "Hackster 2025",
    "description": "HMRITM\u2019s Hackster 2025 is a high-energy, theme-based hackathon with \u20b925,000+ prize pool and on-campus finals in Delhi.",
    "startDate": "2025-08-30T00:01:00+05:30",
    "endDate": "2025-09-06T18:00:00+05:30",
    "registrationEndDate": "2025-08-30T00:00:00+05:30",
    "platform": "unstop",
    "url": "https://unstop.com/hackathons/hackster-2025-hmr-institute-of-technology-and-management-hmritm-new-delhi-1504766",
    "location": "Online + Onsite (HMRITM, Delhi)",
    "teamSize": "2-4 members",
    "prizePool": "\u20b925,000+ + special category prizes",
    "status": "registration_open"
  },
  {
    "id": "4",
    "title": "Hack Quanta",
    "description": "A 36-hour national-level hackathon by JIMS Technical Campus and Geek Room, bringing together innovators to tackle real-world tech challenges.",
    "startDate": "2025-09-05T00:00:00Z",
    "endDate": "2025-09-06T23:59:00Z",
    "registrationEndDate": "2025-09-04T23:59:00Z",
    "platform": "devfolio",
    "url": "https://hack-quanta.devfolio.co/",
    "location": "Greater Noida, India",
    "teamSize": "1-4 members",
    "prizePool": "$560",
    "status": "registration_open"
  },
  {
    "id": "13",
    "title": "Hack4Brahmaputra",
    "description": "Northeast India\u2019s 24-hour hackathon focused on sustainability, connectivity, and preserving indigenous knowledge through tech.",
    "startDate": "2025-09-09T00:00:00Z",
    "endDate": "2025-09-10T23:59:00Z",
    "registrationEndDate": "2025-09-08T23:59:00Z",
    "platform": "devfolio",
    "url": "https://hack4brahmaputra.devfolio.co/",
    "location": "Guwahati, India",
    "teamSize": "3-4 members",
    "prizePool": "$100",
    "status": "registration_open"
  },
  {
    "id": "14",
    "title": "Hack-O-Knight",
    "description": "A high-energy 14-hour hackathon at SYTRON\u201924 in Kolkata organized by IEEE IEM SB to promote innovation and collaboration.",
    "startDate": "2026-02-18T00:00:00Z",
    "endDate": "2026-02-19T23:59:00Z",
    "registrationEndDate": "2026-02-17T23:59:00Z",
    "platform": "devfolio",
    "url": "https://hack-o-knight.devfolio.co/",
    "location": "Kolkata, India",
    "teamSize": "1-5 members",
    "prizePool": "$800",
    "status": "registration_open"
  },
  {
    "id": "15",
    "title": "RNS Hack_Overflow 2.0",
    "description": "RNS Hack_Overflow is a 24-hour Bengaluru-based hackathon encouraging innovation and collaboration among peers in tech.",
    "startDate": "2026-02-21T00:00:00Z",
    "endDate": "2026-02-22T23:59:00Z",
    "registrationEndDate": "2026-02-20T23:59:00Z",
    "platform": "devfolio",
    "url": "https://rns-hackoverflow-2.devfolio.co/",
    "location": "Bengaluru, India",
    "teamSize": "1-4 members",
    "prizePool": "$550",
    "status": "registration_open"
  }
]